cuea/__init__.py
cuea/client.py
cuea/config.py
cuea/errors.py
cuea/models.py
cuea/rate_limiter.py
cuea/registry.py
cuea/transport.py
cuea/utils.py
cuea/adapters/__init__.py
cuea/adapters/_task_names.py
cuea/adapters/_util_marketspec.py
cuea/adapters/base.py
cuea/adapters/binance/__init__.py
cuea/adapters/binance/adapter.py
cuea/adapters/binance/auth.py
cuea/adapters/binance/common.py
cuea/adapters/binance/futures.py
cuea/adapters/binance/margin.py
cuea/adapters/binance/options.py
cuea/adapters/binance/spot.py
cuea/adapters/binance/transport.py
cuea/adapters/bybit/__init__.py
cuea/adapters/bybit/adapter.py
cuea/adapters/bybit/auth.py
cuea/adapters/bybit/common.py
cuea/adapters/bybit/futures.py
cuea/adapters/bybit/margin.py
cuea/adapters/bybit/options.py
cuea/adapters/bybit/spot.py
cuea/adapters/bybit/transport.py
cuea-0.1.1.dist-info/licenses/LICENSE
cuea-0.1.1.dist-info/METADATA
cuea-0.1.1.dist-info/WHEEL
cuea-0.1.1.dist-info/top_level.txt
cuea-0.1.1.dist-info/RECORD
