Metadata-Version: 2.4
Name: cuea
Version: 0.1.1
Summary: Crypto Unified Exchange Adapters — async-first unified models and modular exchange adapters.
Author: QuantFolks
Maintainer: QuantFolks
License: MIT
Keywords: crypto,exchange,websocket,async,trading,finance
Classifier: Development Status :: 3 - Alpha
Classifier: Intended Audience :: Developers
Classifier: License :: OSI Approved :: MIT License
Classifier: Programming Language :: Python :: 3 :: Only
Classifier: Programming Language :: Python :: 3.10
Classifier: Programming Language :: Python :: 3.11
Classifier: Programming Language :: Python :: 3.12
Classifier: Operating System :: OS Independent
Classifier: Topic :: Software Development :: Libraries
Classifier: Topic :: Internet :: WWW/HTTP
Requires-Python: <3.13,>=3.10
License-File: LICENSE
Requires-Dist: aiohttp>=3.8.1
Requires-Dist: pydantic>=1.10
Requires-Dist: python-dotenv>=1.0.0
Provides-Extra: marketspec
Requires-Dist: marketspec>=1.0.1; extra == "marketspec"
Provides-Extra: yaml
Requires-Dist: PyYAML>=6.0; extra == "yaml"
Provides-Extra: dev
Requires-Dist: pytest>=7.0; extra == "dev"
Requires-Dist: pytest-asyncio>=0.20.0; extra == "dev"
Requires-Dist: ruff>=0.0.0; extra == "dev"
Requires-Dist: mypy>=1.0; extra == "dev"
Requires-Dist: sphinx>=5.0; extra == "dev"
Dynamic: license-file
